{
"type": "FeatureCollection",
"name": "nbore",
"crs": { "type": "name", "properties": { "name": "urn:ogc:def:crs:OGC:1.3:CRS84" } },
"features": [
{ "type": "Feature", "properties": { "id": 5, "activity": "New borehole", "date": "2022-03-16", "desc": "Borehole drilled according to Sphere standards with India Mark II installed.", "benific": 487, "dataset_id": "w2" }, "geometry": { "type": "Point", "coordinates": [ -16.090249015601795, 12.674202531147797 ] } },
{ "type": "Feature", "properties": { "id": 8, "activity": "New borehole", "date": "2022-03-31", "desc": "Borehole drilled according to Sphere standards with India Mark II installed.", "benific": 476, "dataset_id": "w2" }, "geometry": { "type": "Point", "coordinates": [ -16.071848524261753, 12.679433315984381 ] } },
{ "type": "Feature", "properties": { "id": 2, "activity": "New borehole", "date": "2022-03-10", "desc": "Borehole drilled according to Sphere standards with India Mark II installed.", "benific": 456, "dataset_id": "w2" }, "geometry": { "type": "Point", "coordinates": [ -16.211336119903983, 12.656803679457315 ] } },
{ "type": "Feature", "properties": { "id": 7, "activity": "New borehole", "date": "2022-02-17", "desc": "Borehole drilled according to Sphere standards with India Mark II installed.", "benific": 467, "dataset_id": "w2" }, "geometry": { "type": "Point", "coordinates": [ -16.534078172079564, 12.553656435915634 ] } },
{ "type": "Feature", "properties": { "id": 9, "activity": "New borehole", "date": "2022-04-22", "desc": "Borehole drilled according to Sphere standards with India Mark II installed.", "benific": 456, "dataset_id": "w2" }, "geometry": { "type": "Point", "coordinates": [ -16.372387564205447, 12.652417641640042 ] } },
{ "type": "Feature", "properties": { "id": 4, "activity": "New borehole", "date": "2022-02-10", "desc": "Borehole drilled according to Sphere standards with India Mark II installed.", "benific": 478, "dataset_id": "w2" }, "geometry": { "type": "Point", "coordinates": [ -16.587503590609952, 12.554843564389186 ] } },
{ "type": "Feature", "properties": { "id": 1, "activity": "New borehole", "date": "2022-03-25", "desc": "Borehole drilled according to Sphere standards with India Mark II installed.", "benific": 489, "dataset_id": "w2" }, "geometry": { "type": "Point", "coordinates": [ -16.550888612000854, 12.493107216050296 ] } },
{ "type": "Feature", "properties": { "id": 11, "activity": "New borehole", "date": "2022-03-21", "desc": "Borehole drilled according to Sphere standards with India Mark II installed.", "benific": 499, "dataset_id": "w2" }, "geometry": { "type": "Point", "coordinates": [ -16.203134164779787, 12.483197990875231 ] } },
{ "type": "Feature", "properties": { "id": 10, "activity": "New borehole", "date": "2022-04-18", "desc": "Borehole drilled according to Sphere standards with India Mark II installed.", "benific": 497, "dataset_id": "w2" }, "geometry": { "type": "Point", "coordinates": [ -16.189630578393128, 12.499883741086819 ] } },
{ "type": "Feature", "properties": { "id": 6, "activity": "New borehole", "date": "2022-03-17", "desc": "Borehole drilled according to Sphere standards with India Mark II installed.", "benific": 487, "dataset_id": "w2" }, "geometry": { "type": "Point", "coordinates": [ -16.113019572110371, 12.57258711614414 ] } },
{ "type": "Feature", "properties": { "id": 3, "activity": "New borehole", "date": "2022-02-24", "desc": "Borehole drilled according to Sphere standards with India Mark II installed.", "benific": 456, "dataset_id": "w2" }, "geometry": { "type": "Point", "coordinates": [ -16.077010008412632, 12.509273597554705 ] } },
{ "type": "Feature", "properties": { "id": 13, "activity": "New borehole", "date": "2022-06-14", "desc": "Borehole drilled according to Sphere standards with India Mark II installed.", "benific": 432, "dataset_id": "w2" }, "geometry": { "type": "Point", "coordinates": [ -16.017865866389148, 12.62788957852403 ] } },
{ "type": "Feature", "properties": { "id": 12, "activity": "New borehole", "date": "2022-03-22", "desc": "Borehole drilled according to Sphere standards with India Mark II installed.", "benific": 489, "dataset_id": "w2" }, "geometry": { "type": "Point", "coordinates": [ -15.99478487372369, 12.617811352420439 ] } }
]
}
