{
"type": "FeatureCollection",
"name": "nbore",
"crs": { "type": "name", "properties": { "name": "urn:ogc:def:crs:OGC:1.3:CRS84" } },
"features": [
{ "type": "Feature", "properties": { "Id": 5, "Activity": "New borehole", "Date": "2022-03-16", "Description": "Borehole drilled according to Sphere standards with India Mark II installed.", "Beneficiaries": 487, "Dataset id": "w2" }, "geometry": { "type": "Point", "coordinates": [ -16.090249015601795, 12.674202531147797 ] } },
{ "type": "Feature", "properties": { "Id": 8, "Activity": "New borehole", "Date": "2022-03-31", "Description": "Borehole drilled according to Sphere standards with India Mark II installed.", "Beneficiaries": 476, "Dataset id": "w2" }, "geometry": { "type": "Point", "coordinates": [ -16.071848524261753, 12.679433315984381 ] } },
{ "type": "Feature", "properties": { "Id": 2, "Activity": "New borehole", "Date": "2022-03-10", "Description": "Borehole drilled according to Sphere standards with India Mark II installed.", "Beneficiaries": 456, "Dataset id": "w2" }, "geometry": { "type": "Point", "coordinates": [ -16.211336119903983, 12.656803679457315 ] } },
{ "type": "Feature", "properties": { "Id": 7, "Activity": "New borehole", "Date": "2022-02-17", "Description": "Borehole drilled according to Sphere standards with India Mark II installed.", "Beneficiaries": 467, "Dataset id": "w2" }, "geometry": { "type": "Point", "coordinates": [ -16.534078172079564, 12.553656435915634 ] } },
{ "type": "Feature", "properties": { "Id": 9, "Activity": "New borehole", "Date": "2022-04-22", "Description": "Borehole drilled according to Sphere standards with India Mark II installed.", "Beneficiaries": 456, "Dataset id": "w2" }, "geometry": { "type": "Point", "coordinates": [ -16.372387564205447, 12.652417641640042 ] } },
{ "type": "Feature", "properties": { "Id": 4, "Activity": "New borehole", "Date": "2022-02-10", "Description": "Borehole drilled according to Sphere standards with India Mark II installed.", "Beneficiaries": 478, "Dataset id": "w2" }, "geometry": { "type": "Point", "coordinates": [ -16.587503590609952, 12.554843564389186 ] } },
{ "type": "Feature", "properties": { "Id": 1, "Activity": "New borehole", "Date": "2022-03-25", "Description": "Borehole drilled according to Sphere standards with India Mark II installed.", "Beneficiaries": 489, "Dataset id": "w2" }, "geometry": { "type": "Point", "coordinates": [ -16.550888612000854, 12.493107216050296 ] } },
{ "type": "Feature", "properties": { "Id": 11, "Activity": "New borehole", "Date": "2022-03-21", "Description": "Borehole drilled according to Sphere standards with India Mark II installed.", "Beneficiaries": 499, "Dataset id": "w2" }, "geometry": { "type": "Point", "coordinates": [ -16.203134164779787, 12.483197990875231 ] } },
{ "type": "Feature", "properties": { "Id": 10, "Activity": "New borehole", "Date": "2022-04-18", "Description": "Borehole drilled according to Sphere standards with India Mark II installed.", "Beneficiaries": 497, "Dataset id": "w2" }, "geometry": { "type": "Point", "coordinates": [ -16.189630578393128, 12.499883741086819 ] } },
{ "type": "Feature", "properties": { "Id": 6, "Activity": "New borehole", "Date": "2022-03-17", "Description": "Borehole drilled according to Sphere standards with India Mark II installed.", "Beneficiaries": 487, "Dataset id": "w2" }, "geometry": { "type": "Point", "coordinates": [ -16.113019572110371, 12.57258711614414 ] } },
{ "type": "Feature", "properties": { "Id": 3, "Activity": "New borehole", "Date": "2022-02-24", "Description": "Borehole drilled according to Sphere standards with India Mark II installed.", "Beneficiaries": 456, "Dataset id": "w2" }, "geometry": { "type": "Point", "coordinates": [ -16.077010008412632, 12.509273597554705 ] } },
{ "type": "Feature", "properties": { "Id": 13, "Activity": "New borehole", "Date": "2022-06-14", "Description": "Borehole drilled according to Sphere standards with India Mark II installed.", "Beneficiaries": 432, "Dataset id": "w2" }, "geometry": { "type": "Point", "coordinates": [ -16.017865866389148, 12.62788957852403 ] } },
{ "type": "Feature", "properties": { "Id": 12, "Activity": "New borehole", "Date": "2022-03-22", "Description": "Borehole drilled according to Sphere standards with India Mark II installed.", "Beneficiaries": 489, "Dataset id": "w2" }, "geometry": { "type": "Point", "coordinates": [ -15.99478487372369, 12.617811352420439 ] } }
]
}
