{
"type": "FeatureCollection",
"name": "boatc",
"crs": { "type": "name", "properties": { "name": "urn:ogc:def:crs:OGC:1.3:CRS84" } },
"features": [
{ "type": "Feature", "properties": { "id": 9, "activity": "Mobile boat clinic", "date": "2022-05-10", "desc": "Mobile clinic staffed with general practioner and nursing staff for general consultation.", "benefic": 45, "dataset_id": "h5" }, "geometry": { "type": "Point", "coordinates": [ -16.664910485519915, 12.504132772527274 ] } },
{ "type": "Feature", "properties": { "id": 10, "activity": "Mobile boat clinic", "date": "2022-05-27", "desc": "Mobile clinic staffed with general practioner and nursing staff for general consultation.", "benefic": 65, "dataset_id": "h5" }, "geometry": { "type": "Point", "coordinates": [ -16.689914040858572, 12.4860564804394 ] } },
{ "type": "Feature", "properties": { "id": 7, "activity": "Mobile boat clinic", "date": "2022-05-26", "desc": "Mobile clinic staffed with general practioner and nursing staff for general consultation.", "benefic": 33, "dataset_id": "h5" }, "geometry": { "type": "Point", "coordinates": [ -16.68331381578701, 12.492121552126779 ] } },
{ "type": "Feature", "properties": { "id": 8, "activity": "Mobile boat clinic", "date": "2022-05-17", "desc": "Mobile clinic staffed with general practioner and nursing staff for general consultation.", "benefic": 43, "dataset_id": "h5" }, "geometry": { "type": "Point", "coordinates": [ -16.668864674414134, 12.45938800346107 ] } },
{ "type": "Feature", "properties": { "id": 1, "activity": "Mobile boat clinic", "date": "2022-05-25", "desc": "Mobile clinic staffed with general practioner and nursing staff for general consultation.", "benefic": 45, "dataset_id": "h5" }, "geometry": { "type": "Point", "coordinates": [ -16.691460039523978, 12.430846489638109 ] } },
{ "type": "Feature", "properties": { "id": 2, "activity": "Mobile boat clinic", "date": "2022-05-12", "desc": "Mobile clinic staffed with general practioner and nursing staff for general consultation.", "benefic": 64, "dataset_id": "h5" }, "geometry": { "type": "Point", "coordinates": [ -16.701449569362016, 12.509335652651254 ] } },
{ "type": "Feature", "properties": { "id": 11, "activity": "Mobile boat clinic", "date": "2022-05-06", "desc": "Mobile clinic staffed with general practioner and nursing staff for general consultation.", "benefic": 32, "dataset_id": "h5" }, "geometry": { "type": "Point", "coordinates": [ -16.712152637045627, 12.507670731011581 ] } },
{ "type": "Feature", "properties": { "id": 12, "activity": "Mobile boat clinic", "date": "2022-05-12", "desc": "Mobile clinic staffed with general practioner and nursing staff for general consultation.", "benefic": 32, "dataset_id": "h5" }, "geometry": { "type": "Point", "coordinates": [ -16.736412923795143, 12.530028250172903 ] } },
{ "type": "Feature", "properties": { "id": 5, "activity": "Mobile boat clinic", "date": "2022-05-06", "desc": "Mobile clinic staffed with general practioner and nursing staff for general consultation.", "benefic": 34, "dataset_id": "h5" }, "geometry": { "type": "Point", "coordinates": [ -16.447073327414866, 12.493043205177313 ] } },
{ "type": "Feature", "properties": { "id": 6, "activity": "Mobile boat clinic", "date": "2022-05-06", "desc": "Mobile clinic staffed with general practioner and nursing staff for general consultation.", "benefic": 54, "dataset_id": "h5" }, "geometry": { "type": "Point", "coordinates": [ -16.458965624841099, 12.448209243880411 ] } },
{ "type": "Feature", "properties": { "id": 3, "activity": "Mobile boat clinic", "date": "2022-05-16", "desc": "Mobile clinic staffed with general practioner and nursing staff for general consultation.", "benefic": 45, "dataset_id": "h5" }, "geometry": { "type": "Point", "coordinates": [ -16.531389716166863, 12.558212995073077 ] } },
{ "type": "Feature", "properties": { "id": 4, "activity": "Mobile boat clinic", "date": "2022-05-06", "desc": "Mobile clinic staffed with general practioner and nursing staff for general consultation.", "benefic": 34, "dataset_id": "h5" }, "geometry": { "type": "Point", "coordinates": [ -16.340994034372851, 12.666195055703287 ] } }
]
}
