{
"type": "FeatureCollection",
"name": "womenh",
"crs": { "type": "name", "properties": { "name": "urn:ogc:def:crs:OGC:1.3:CRS84" } },
"features": [
{ "type": "Feature", "properties": { "id": 3, "activity": "Women's health consultation", "date": "2022-02-22", "desc": "Comprehensive examination including: pelvic exam, pap smear, breast exam.", "benefic": 56, "dataset_id": "h4" }, "geometry": { "type": "Point", "coordinates": [ -16.271166928408828, 12.585080570419146 ] } },
{ "type": "Feature", "properties": { "id": 1, "activity": "Women's health consultation", "date": "2022-01-27", "desc": "Comprehensive examination including: pelvic exam, pap smear, breast exam.", "benefic": 79, "dataset_id": "h4" }, "geometry": { "type": "Point", "coordinates": [ -16.276240428165604, 12.562302828227544 ] } },
{ "type": "Feature", "properties": { "id": 2, "activity": "Women's health consultation", "date": "2022-02-16", "desc": "Comprehensive examination including: pelvic exam, pap smear, breast exam.", "benefic": 92, "dataset_id": "h4" }, "geometry": { "type": "Point", "coordinates": [ -16.294293000434475, 12.570157287365923 ] } },
{ "type": "Feature", "properties": { "id": 6, "activity": "Women's health consultation", "date": "2022-01-26", "desc": "Comprehensive examination including: pelvic exam, pap smear, breast exam.", "benefic": 145, "dataset_id": "h4" }, "geometry": { "type": "Point", "coordinates": [ -16.580826116630295, 12.5564102090954 ] } },
{ "type": "Feature", "properties": { "id": 7, "activity": "Women's health consultation", "date": "2022-05-30", "desc": "Comprehensive examination including: pelvic exam, pap smear, breast exam.", "benefic": 45, "dataset_id": "h4" }, "geometry": { "type": "Point", "coordinates": [ -16.535765203818507, 12.557649714306503 ] } },
{ "type": "Feature", "properties": { "id": 4, "activity": "Women's health consultation", "date": "2022-02-11", "desc": "Comprehensive examination including: pelvic exam, pap smear, breast exam.", "benefic": 79, "dataset_id": "h4" }, "geometry": { "type": "Point", "coordinates": [ -16.513553497607216, 12.456237458627168 ] } },
{ "type": "Feature", "properties": { "id": 5, "activity": "Women's health consultation", "date": "2021-12-20", "desc": "Comprehensive examination including: pelvic exam, pap smear, breast exam.", "benefic": 34, "dataset_id": "h4" }, "geometry": { "type": "Point", "coordinates": [ -16.18582434428868, 12.495583585099132 ] } }
]
}
