{
"type": "FeatureCollection",
"name": "womenh",
"crs": { "type": "name", "properties": { "name": "urn:ogc:def:crs:OGC:1.3:CRS84" } },
"features": [
{ "type": "Feature", "properties": { "Id": 1, "Activity": "Women's health consultation", "Date": "2022-01-27", "Description": "Comprehensive examination including: pelvic exam, pap smear, breast exam.", "Beneficiaries": 79, "Dataset_id": "h4" }, "geometry": { "type": "Point", "coordinates": [ -16.276240428165604, 12.562302828227544 ] } },
{ "type": "Feature", "properties": { "Id": 2, "Activity": "Women's health consultation", "Date": "2022-02-16", "Description": "Comprehensive examination including: pelvic exam, pap smear, breast exam.", "Beneficiaries": 92, "Dataset_id": "h4" }, "geometry": { "type": "Point", "coordinates": [ -16.294293000434475, 12.570157287365923 ] } },
{ "type": "Feature", "properties": { "Id": 6, "Activity": "Women's health consultation", "Date": "2022-01-26", "Description": "Comprehensive examination including: pelvic exam, pap smear, breast exam.", "Beneficiaries": 145, "Dataset_id": "h4" }, "geometry": { "type": "Point", "coordinates": [ -16.580826116630295, 12.5564102090954 ] } },
{ "type": "Feature", "properties": { "Id": 7, "Activity": "Women's health consultation", "Date": "2022-05-30", "Description": "Comprehensive examination including: pelvic exam, pap smear, breast exam.", "Beneficiaries": 45, "Dataset_id": "h4" }, "geometry": { "type": "Point", "coordinates": [ -16.535765203818507, 12.557649714306503 ] } },
{ "type": "Feature", "properties": { "Id": 4, "Activity": "Women's health consultation", "Date": "2022-02-11", "Description": "Comprehensive examination including: pelvic exam, pap smear, breast exam.", "Beneficiaries": 79, "Dataset_id": "h4" }, "geometry": { "type": "Point", "coordinates": [ -16.513553497607216, 12.456237458627168 ] } },
{ "type": "Feature", "properties": { "Id": 5, "Activity": "Women's health consultation", "Date": "2021-12-20", "Description": "Comprehensive examination including: pelvic exam, pap smear, breast exam.", "Beneficiaries": 34, "Dataset_id": "h4" }, "geometry": { "type": "Point", "coordinates": [ -16.18582434428868, 12.495583585099132 ] } }
]
}
